cryptocloud_sdk/__init__.py
cryptocloud_sdk/dto/__init__.py
cryptocloud_sdk/dto/balance.py
cryptocloud_sdk/dto/currency.py
cryptocloud_sdk/dto/invoice.py
cryptocloud_sdk/dto/network.py
cryptocloud_sdk/dto/postback.py
cryptocloud_sdk/dto/project.py
cryptocloud_sdk/dto/static_wallet.py
cryptocloud_sdk/dto/stats.py
cryptocloud_sdk/errors.py
cryptocloud_sdk/http_executor.py
cryptocloud_sdk/merchant.py
cryptocloud_sdk-0.1.1.dist-info/METADATA
cryptocloud_sdk-0.1.1.dist-info/WHEEL
cryptocloud_sdk-0.1.1.dist-info/RECORD
