Metadata-Version: 2.3
Name: cryptocloud-sdk
Version: 0.1.1
Summary: 
Keywords: async,crypto cloud,python,sdk
Author: Никита Прожога
Author-email: fofmow@gmail.com
Requires-Python: >=3.10
Classifier: Programming Language :: Python :: 3.10
Classifier: License :: OSI Approved :: MIT License
Classifier: Operating System :: OS Independent
Requires-Dist: aiohttp (>=3.11.11,<4.0.0)
Requires-Dist: pydantic (>=2.10.5,<3.0.0)
Project-URL: Homepage, https://github.com/fofmow/crypto-cloud-sdk
Project-URL: Repository, https://github.com/fofmow/crypto-cloud-sdk
